{
	"commonModules": [
		{
			"name": "РаботаСДокументами",
			"export": true,
			"server": false,
			"client": true
		},
		{
			"name": "РаботаСоСправочниками",
			"export": true,
			"server": true,
			"client": false
		}
	],
	"catalogs": [
		{
			"name": "ДоговорыКонтрагентов",
			"uuid": "beb51ad2-37d0-4346-aa08-c0a05d8634a9",
			"attributes": [
				{
					"uuid": "490f624f-d7f3-4ac1-8e74-e90edfe4ee75",
					"name": "Номер",
					"type": {
						"kind": "string",
						"length": 50
					},
					"required": false
				},
				{
					"uuid": "57151dce-bc9b-4dcd-a8b5-f12b1e9906c5",
					"name": "Дата",
					"type": {
						"kind": "date"
					},
					"required": false
				}
			],
			"standardAttributes": [
				{
					"name": "Ref",
					"synonym": "Ссылка",
					"type": {
						"kind": "ref",
						"target": "Catalog.ДоговорыКонтрагентов"
					},
					"required": true
				},
				{
					"name": "DataVersion",
					"synonym": "ВерсияДанных",
					"type": {
						"kind": "number",
						"precision": 15,
						"scale": 0
					},
					"required": true
				},
				{
					"name": "DeletionMark",
					"synonym": "ПометкаУдаления",
					"type": {
						"kind": "boolean"
					},
					"required": false
				},
				{
					"name": "Code",
					"synonym": "Код",
					"type": {
						"kind": "string",
						"length": 9
					},
					"required": false
				},
				{
					"name": "Description",
					"synonym": "Наименование",
					"type": {
						"kind": "string",
						"length": 25
					},
					"required": false
				},
				{
					"name": "PredefinedDataName",
					"synonym": "ИмяПредопределенныхДанных",
					"type": {
						"kind": "string",
						"length": 80
					},
					"required": false
				},
				{
					"name": "Predefined",
					"synonym": "Предопределенный",
					"type": {
						"kind": "boolean"
					},
					"required": false
				},
				{
					"name": "Owner",
					"synonym": "Владелец",
					"type": {
						"kind": "ref",
						"target": "Catalog.Контрагенты"
					},
					"required": true
				}
			],
			"tabularSections": [],
			"forms": [
				{
					"name": "ФормаЭлемента",
					"type": "managed"
				}
			],
			"commands": [],
			"predefinedItems": null
		},
		{
			"name": "Контрагенты",
			"uuid": "8e0d9c78-5268-48fa-838d-bde0a9da699a",
			"attributes": [],
			"standardAttributes": [
				{
					"name": "Ref",
					"synonym": "Ссылка",
					"type": {
						"kind": "ref",
						"target": "Catalog.Контрагенты"
					},
					"required": true
				},
				{
					"name": "DataVersion",
					"synonym": "ВерсияДанных",
					"type": {
						"kind": "number",
						"precision": 15,
						"scale": 0
					},
					"required": true
				},
				{
					"name": "DeletionMark",
					"synonym": "ПометкаУдаления",
					"type": {
						"kind": "boolean"
					},
					"required": false
				},
				{
					"name": "Code",
					"synonym": "Код",
					"type": {
						"kind": "string",
						"length": 9
					},
					"required": false
				},
				{
					"name": "Description",
					"synonym": "Наименование",
					"type": {
						"kind": "string",
						"length": 100
					},
					"required": false
				},
				{
					"name": "Parent",
					"synonym": "Родитель",
					"type": {
						"kind": "ref",
						"target": "Catalog.Контрагенты"
					},
					"required": false
				},
				{
					"name": "IsFolder",
					"synonym": "ЭтоГруппа",
					"type": {
						"kind": "boolean"
					},
					"required": false
				},
				{
					"name": "PredefinedDataName",
					"synonym": "ИмяПредопределенныхДанных",
					"type": {
						"kind": "string",
						"length": 80
					},
					"required": false
				},
				{
					"name": "Predefined",
					"synonym": "Предопределенный",
					"type": {
						"kind": "boolean"
					},
					"required": false
				}
			],
			"tabularSections": [],
			"forms": [],
			"commands": [],
			"predefinedItems": null
		},
		{
			"name": "Номенклатура",
			"uuid": "5d3e9322-448e-4731-a85a-5d4d344a0c7c",
			"attributes": [
				{
					"uuid": "f45cd5fd-f885-4ddf-b262-c48b5de94ffd",
					"name": "ВидНоменклатуры",
					"type": {
						"kind": "enum",
						"target": "ВидыНоменклатуры"
					},
					"required": false
				}
			],
			"standardAttributes": [
				{
					"name": "Ref",
					"synonym": "Ссылка",
					"type": {
						"kind": "ref",
						"target": "Catalog.Номенклатура"
					},
					"required": true
				},
				{
					"name": "DataVersion",
					"synonym": "ВерсияДанных",
					"type": {
						"kind": "number",
						"precision": 15,
						"scale": 0
					},
					"required": true
				},
				{
					"name": "DeletionMark",
					"synonym": "ПометкаУдаления",
					"type": {
						"kind": "boolean"
					},
					"required": false
				},
				{
					"name": "Code",
					"synonym": "Код",
					"type": {
						"kind": "string",
						"length": 9
					},
					"required": false
				},
				{
					"name": "Description",
					"synonym": "Наименование",
					"type": {
						"kind": "string",
						"length": 100
					},
					"required": false
				},
				{
					"name": "Parent",
					"synonym": "Родитель",
					"type": {
						"kind": "ref",
						"target": "Catalog.Номенклатура"
					},
					"required": false
				},
				{
					"name": "IsFolder",
					"synonym": "ЭтоГруппа",
					"type": {
						"kind": "boolean"
					},
					"required": false
				},
				{
					"name": "PredefinedDataName",
					"synonym": "ИмяПредопределенныхДанных",
					"type": {
						"kind": "string",
						"length": 80
					},
					"required": false
				},
				{
					"name": "Predefined",
					"synonym": "Предопределенный",
					"type": {
						"kind": "boolean"
					},
					"required": false
				}
			],
			"tabularSections": [],
			"forms": [],
			"commands": [],
			"predefinedItems": null
		},
		{
			"name": "Склады",
			"uuid": "392b6f66-fa32-4851-97af-9d66f1ab6e9a",
			"attributes": [],
			"standardAttributes": [
				{
					"name": "Ref",
					"synonym": "Ссылка",
					"type": {
						"kind": "ref",
						"target": "Catalog.Склады"
					},
					"required": true
				},
				{
					"name": "DataVersion",
					"synonym": "ВерсияДанных",
					"type": {
						"kind": "number",
						"precision": 15,
						"scale": 0
					},
					"required": true
				},
				{
					"name": "DeletionMark",
					"synonym": "ПометкаУдаления",
					"type": {
						"kind": "boolean"
					},
					"required": false
				},
				{
					"name": "Code",
					"synonym": "Код",
					"type": {
						"kind": "string",
						"length": 9
					},
					"required": false
				},
				{
					"name": "Description",
					"synonym": "Наименование",
					"type": {
						"kind": "string",
						"length": 50
					},
					"required": false
				},
				{
					"name": "PredefinedDataName",
					"synonym": "ИмяПредопределенныхДанных",
					"type": {
						"kind": "string",
						"length": 80
					},
					"required": false
				},
				{
					"name": "Predefined",
					"synonym": "Предопределенный",
					"type": {
						"kind": "boolean"
					},
					"required": false
				}
			],
			"tabularSections": [],
			"forms": [],
			"commands": [],
			"predefinedItems": [
				{
					"name": "Основной",
					"uuid": "0682f136-817a-48f3-8459-3eb07fe4b9bd"
				}
			]
		},
		{
			"name": "Сотрудники",
			"uuid": "79e98965-5139-4369-9779-93931deafbdf",
			"attributes": [],
			"standardAttributes": [
				{
					"name": "Ref",
					"synonym": "Ссылка",
					"type": {
						"kind": "ref",
						"target": "Catalog.Сотрудники"
					},
					"required": true
				},
				{
					"name": "DataVersion",
					"synonym": "ВерсияДанных",
					"type": {
						"kind": "number",
						"precision": 15,
						"scale": 0
					},
					"required": true
				},
				{
					"name": "DeletionMark",
					"synonym": "ПометкаУдаления",
					"type": {
						"kind": "boolean"
					},
					"required": false
				},
				{
					"name": "Code",
					"synonym": "Код",
					"type": {
						"kind": "string",
						"length": 9
					},
					"required": false
				},
				{
					"name": "Description",
					"synonym": "Наименование",
					"type": {
						"kind": "string",
						"length": 50
					},
					"required": false
				},
				{
					"name": "PredefinedDataName",
					"synonym": "ИмяПредопределенныхДанных",
					"type": {
						"kind": "string",
						"length": 80
					},
					"required": false
				},
				{
					"name": "Predefined",
					"synonym": "Предопределенный",
					"type": {
						"kind": "boolean"
					},
					"required": false
				}
			],
			"tabularSections": [
				{
					"uuid": "07a0a990-75c6-49cd-877f-c2234be8741d",
					"name": "ТрудоваяДеятельность",
					"attributes": [
						{
							"uuid": "f0b61617-72a2-42d0-b81e-be6de741e314",
							"name": "Организация",
							"type": {
								"kind": "string",
								"length": 100
							},
							"required": false
						},
						{
							"uuid": "b2c4542a-a401-400a-8c41-bf7c95b351b4",
							"name": "НачалоРаботы",
							"type": {
								"kind": "date"
							},
							"required": false
						},
						{
							"uuid": "c58b75c7-3a1a-445f-8ace-2283570d3ae0",
							"name": "ОкончаниеРаботы",
							"type": {
								"kind": "date"
							},
							"required": false
						},
						{
							"uuid": "9e941e71-8052-4efb-846d-e76489e7e666",
							"name": "Должность",
							"type": {
								"kind": "string",
								"length": 100
							},
							"required": false
						}
					],
					"standardAttributes": [
						{
							"name": "Ref",
							"synonym": "Ссылка",
							"type": {
								"kind": "ref",
								"target": "Catalog.ТрудоваяДеятельность"
							},
							"required": true
						},
						{
							"name": "LineNumber",
							"synonym": "НомерСтроки",
							"type": {
								"kind": "number",
								"precision": 5,
								"scale": 0
							},
							"required": true
						}
					]
				}
			],
			"forms": [],
			"commands": [],
			"predefinedItems": null
		}
	],
	"documents": [
		{
			"name": "ОказаниеУслуги",
			"uuid": "4204cb6f-9a07-46b6-bc9a-36d6d9ee4271",
			"attributes": [
				{
					"uuid": "345ef996-4c43-46b0-8c99-8f2ee3a1c403",
					"name": "Склад",
					"type": {
						"kind": "ref",
						"target": "Catalog.Склады"
					},
					"required": false
				},
				{
					"uuid": "bf1afab8-f3fe-4165-bf35-a186a1a49c72",
					"name": "Клиент",
					"type": {
						"kind": "ref",
						"target": "Catalog.Контрагенты"
					},
					"required": true
				},
				{
					"uuid": "8cd6e9f8-f735-42db-b754-81e68bf6b794",
					"name": "Мастер",
					"type": {
						"kind": "ref",
						"target": "Catalog.Сотрудники"
					},
					"required": true
				},
				{
					"uuid": "b6a2c818-0dcf-4c58-a295-6a6ae10ebb2b",
					"name": "ИтоговаяСумма",
					"type": {
						"kind": "number",
						"precision": 15,
						"scale": 2
					},
					"required": false
				},
				{
					"uuid": "f65e386e-6a14-4142-b399-d7edd212d55f",
					"name": "ДоговорКонтрагента",
					"type": {
						"kind": "ref",
						"target": "Catalog.ДоговорыКонтрагентов"
					},
					"required": true
				}
			],
			"standardAttributes": [
				{
					"name": "Ref",
					"synonym": "Ссылка",
					"type": {
						"kind": "ref",
						"target": "Document.ОказаниеУслуги"
					},
					"required": true
				},
				{
					"name": "DataVersion",
					"synonym": "ВерсияДанных",
					"type": {
						"kind": "number",
						"precision": 15,
						"scale": 0
					},
					"required": true
				},
				{
					"name": "DeletionMark",
					"synonym": "ПометкаУдаления",
					"type": {
						"kind": "boolean"
					},
					"required": false
				},
				{
					"name": "Number",
					"synonym": "Номер",
					"type": {
						"kind": "string",
						"length": 9
					},
					"required": false
				},
				{
					"name": "Date",
					"synonym": "Дата",
					"type": {
						"kind": "date"
					},
					"required": true
				},
				{
					"name": "Posted",
					"synonym": "Проведен",
					"type": {
						"kind": "boolean"
					},
					"required": false
				}
			],
			"tabularSections": [
				{
					"uuid": "03dfe023-d6d1-467d-8c17-b1475dcc6a95",
					"name": "ПереченьНоменклатуры",
					"attributes": [
						{
							"uuid": "f76cdca8-51ad-481d-bf65-e194e32aeaf0",
							"name": "Номенклатура",
							"type": {
								"kind": "ref",
								"target": "Catalog.Номенклатура"
							},
							"required": true
						},
						{
							"uuid": "6b085701-5e58-4fad-8288-55eec8bcc071",
							"name": "Стоимость",
							"type": {
								"kind": "number",
								"precision": 15,
								"scale": 2
							},
							"required": false
						},
						{
							"uuid": "530e63c0-696d-4343-bbe9-a4807a6581bc",
							"name": "Количество",
							"type": {
								"kind": "number",
								"precision": 15,
								"scale": 3
							},
							"required": true
						},
						{
							"uuid": "c26db247-c72a-4186-a28b-e5e618d02e68",
							"name": "Цена",
							"type": {
								"kind": "number",
								"precision": 15,
								"scale": 2
							},
							"required": true
						},
						{
							"uuid": "ef7f94ac-f56c-41ab-b033-0b4c015c82a3",
							"name": "Сумма",
							"type": {
								"kind": "number",
								"precision": 15,
								"scale": 2
							},
							"required": true
						}
					],
					"standardAttributes": [
						{
							"name": "Ref",
							"synonym": "Ссылка",
							"type": {
								"kind": "ref",
								"target": "Document.ПереченьНоменклатуры"
							},
							"required": true
						},
						{
							"name": "LineNumber",
							"synonym": "НомерСтроки",
							"type": {
								"kind": "number",
								"precision": 5,
								"scale": 0
							},
							"required": true
						}
					]
				}
			],
			"forms": [
				{
					"name": "ФормаДокумента",
					"type": "managed"
				}
			],
			"commands": [
				{
					"uuid": "d34e62bf-b83c-4a95-9241-dd2b3df08839",
					"name": "Печать",
					"handler": "ОбработкаКоманды"
				}
			]
		},
		{
			"name": "ПриходнаяНакладная",
			"uuid": "3c5ed7d9-ea2c-46cf-bd15-cbc1c9496e82",
			"attributes": [
				{
					"uuid": "43511035-619e-4b53-b7d5-f62add3db4e3",
					"name": "Склад",
					"type": {
						"kind": "ref",
						"target": "Catalog.Склады"
					},
					"required": true
				}
			],
			"standardAttributes": [
				{
					"name": "Ref",
					"synonym": "Ссылка",
					"type": {
						"kind": "ref",
						"target": "Document.ПриходнаяНакладная"
					},
					"required": true
				},
				{
					"name": "DataVersion",
					"synonym": "ВерсияДанных",
					"type": {
						"kind": "number",
						"precision": 15,
						"scale": 0
					},
					"required": true
				},
				{
					"name": "DeletionMark",
					"synonym": "ПометкаУдаления",
					"type": {
						"kind": "boolean"
					},
					"required": false
				},
				{
					"name": "Number",
					"synonym": "Номер",
					"type": {
						"kind": "string",
						"length": 9
					},
					"required": false
				},
				{
					"name": "Date",
					"synonym": "Дата",
					"type": {
						"kind": "date"
					},
					"required": true
				},
				{
					"name": "Posted",
					"synonym": "Проведен",
					"type": {
						"kind": "boolean"
					},
					"required": false
				}
			],
			"tabularSections": [
				{
					"uuid": "ac74206f-b2df-4db8-b206-2214f0c1f504",
					"name": "Материалы",
					"attributes": [
						{
							"uuid": "77e905ae-635f-41d7-8153-94a422ffbe52",
							"name": "Материал",
							"type": {
								"kind": "ref",
								"target": "Catalog.Номенклатура"
							},
							"required": true
						},
						{
							"uuid": "9c2876fb-f343-4c4d-b1ea-9fb1906dca38",
							"name": "Количество",
							"type": {
								"kind": "number",
								"precision": 15,
								"scale": 3
							},
							"required": true
						},
						{
							"uuid": "113969d3-3fa5-473a-b74d-c06a0f7c68eb",
							"name": "Цена",
							"type": {
								"kind": "number",
								"precision": 15,
								"scale": 2
							},
							"required": true
						},
						{
							"uuid": "11430174-99cf-4bf5-8dac-52fc75711458",
							"name": "Сумма",
							"type": {
								"kind": "number",
								"precision": 15,
								"scale": 2
							},
							"required": true
						}
					],
					"standardAttributes": [
						{
							"name": "Ref",
							"synonym": "Ссылка",
							"type": {
								"kind": "ref",
								"target": "Document.Материалы"
							},
							"required": true
						},
						{
							"name": "LineNumber",
							"synonym": "НомерСтроки",
							"type": {
								"kind": "number",
								"precision": 5,
								"scale": 0
							},
							"required": true
						}
					]
				}
			],
			"forms": [
				{
					"name": "ФормаДокумента",
					"type": "managed"
				}
			],
			"commands": []
		}
	],
	"enumerations": [
		{
			"name": "ВидыНоменклатуры",
			"uuid": "c52e6681-3d94-4d9e-8b9b-32f6d324ebee",
			"values": [
				{
					"uuid": "a6d8c85e-de59-4f8d-b8cf-3ebc679d5051",
					"name": "Материал"
				},
				{
					"uuid": "3ea3967a-6238-48d3-910b-ed63610b6c3b",
					"name": "Услуга"
				}
			]
		}
	],
	"configurationName": "МастерскаяРадченко",
	"configurationUuid": "3f521541-0317-484a-8e71-282d009c0c5d",
	"version": "2"
}